otter_ai/__init__.py
otter_ai/models/__init__.py
otter_ai/models/falcon/__init__.py
otter_ai/models/falcon/configuration_RW.py
otter_ai/models/falcon/modelling_RW.py
otter_ai/models/flamingo/__init__.py
otter_ai/models/flamingo/configuration_flamingo.py
otter_ai/models/flamingo/converting_flamingo_to_bf16.py
otter_ai/models/flamingo/converting_flamingo_to_hf.py
otter_ai/models/flamingo/converting_flamingo_to_lora.py
otter_ai/models/flamingo/injecting_falcon_into_flamingo.py
otter_ai/models/flamingo/injecting_llama2_into_flamingo.py
otter_ai/models/flamingo/injecting_mpt-1B-redpajama_into_flamingo.py
otter_ai/models/flamingo/injecting_mpt_into_flamingo.py
otter_ai/models/flamingo/injecting_vicuna_into_flamingo.py
otter_ai/models/flamingo/modeling_flamingo.py
otter_ai/models/flamingo/utils.py
otter_ai/models/mpt/__init__.py
otter_ai/models/mpt/adapt_tokenizer.py
otter_ai/models/mpt/attention.py
otter_ai/models/mpt/blocks.py
otter_ai/models/mpt/configuration_mpt.py
otter_ai/models/mpt/custom_embedding.py
otter_ai/models/mpt/flash_attn_triton.py
otter_ai/models/mpt/hf_prefixlm_converter.py
otter_ai/models/mpt/meta_init_context.py
otter_ai/models/mpt/modeling_mpt.py
otter_ai/models/mpt/norm.py
otter_ai/models/mpt/param_init_fns.py
otter_ai/models/mpt_redpajama/__init__.py
otter_ai/models/mpt_redpajama/attention.py
otter_ai/models/mpt_redpajama/configuration_mosaic_gpt.py
otter_ai/models/mpt_redpajama/gpt_blocks.py
otter_ai/models/mpt_redpajama/low_precision_layernorm.py
otter_ai/models/mpt_redpajama/mosaic_gpt.py
otter_ai/models/mpt_redpajama/param_init_fns.py
otter_ai/models/otter/__init__.py
otter_ai/models/otter/configuration_otter.py
otter_ai/models/otter/converting_flamingo_to_otter.py
otter_ai/models/otter/converting_otter_fp32_to_fp16.py
otter_ai/models/otter/converting_otter_pt_to_hf.py
otter_ai/models/otter/converting_otter_to_lora.py
otter_ai/models/otter/flamingo_pt2otter_hf.py
otter_ai/models/otter/modeling_otter.py
otter_ai-0.0.0a8.dist-info/LICENSE
otter_ai-0.0.0a8.dist-info/METADATA
otter_ai-0.0.0a8.dist-info/WHEEL
otter_ai-0.0.0a8.dist-info/top_level.txt
otter_ai-0.0.0a8.dist-info/RECORD
