Metadata-Version: 2.1
Name: otter-ai
Version: 0.0.0a8
Summary: Otter: A Multi-Modal Model with In-Context Instruction Tuning
Home-page: https://github.com/Luodian/Otter
Author: Otter Team
Author-email: drluodian@gmail.com
Classifier: Development Status :: 3 - Alpha
Classifier: Intended Audience :: Developers
Classifier: Programming Language :: Python :: 3
Classifier: Programming Language :: Python :: 3.9
Classifier: Programming Language :: Python :: 3.10
Classifier: Programming Language :: Python :: 3.11
License-File: LICENSE
Requires-Dist: accelerate >=0.19.0
Requires-Dist: braceexpand >=0.1.7
Requires-Dist: einops >=0.6.1
Requires-Dist: einops-exts >=0.0.4
Requires-Dist: fastapi >=0.95.2
Requires-Dist: gradio >=3.33.1
Requires-Dist: huggingface-hub >=0.13.3
Requires-Dist: importlib-metadata >=6.6.0
Requires-Dist: inflection >=0.5.1
Requires-Dist: markdown2 >=2.4.8
Requires-Dist: more-itertools >=9.1.0
Requires-Dist: nltk >=3.8.1
Requires-Dist: numpy >=1.23.5
Requires-Dist: open-clip-torch >=2.16.0
Requires-Dist: openai >=1.1.1
Requires-Dist: opencv-python-headless >=4.5.5.64
Requires-Dist: Pillow >=9.5.0
Requires-Dist: pycocoevalcap >=1
Requires-Dist: pycocotools >=2.0.6
Requires-Dist: Requests >=2.31.0
Requires-Dist: scipy >=1.10.1
Requires-Dist: timm >=0.9.2
Requires-Dist: tqdm >=4.65.0
Requires-Dist: transformers ==4.35.1
Requires-Dist: uvicorn >=0.22.0
Requires-Dist: webdataset >=0.2.48
Requires-Dist: natsort >=8.4.0
Requires-Dist: peft >=0.4.0
Requires-Dist: ijson >=3.2.3
Requires-Dist: yajl >=0.3.5
Requires-Dist: deepspeed >=0.10.0
Requires-Dist: wandb >=0.15.8
Requires-Dist: trl >=0.5.0
Requires-Dist: cffi >=1.15.1
Requires-Dist: pyyaml >=6.0.1
Requires-Dist: pytest >=7.4.2
Requires-Dist: prettytable >=3.9.0
